[
  {
    "name": "gcd",
    "by_3gram_simpson": 0.21985817
  },
  {
    "name": "binarysearch",
    "by_3gram_simpson": 0.27160496
  },
  {
    "name": "numtowords",
    "by_3gram_simpson": 0.23333335
  },
  {
    "name": "stringtoASCII",
    "by_3gram_simpson": 0.11570245
  },
  {
    "name": "prime",
    "by_3gram_simpson": 0.22556388
  },
  {
    "name": "decimaltobinary",
    "by_3gram_simpson": 0.18840581
  },
  {
    "name": "minmaxarray",
    "by_3gram_simpson": 0.24113476
  },
  {
    "name": "frequency",
    "by_3gram_simpson": 0.17213112
  },
  {
    "name": "vowels",
    "by_3gram_simpson": 0.23571426
  },
  {
    "name": "pyramid",
    "by_3gram_simpson": 0.1512605
  },
  {
    "name": "bubblesort",
    "by_3gram_simpson": 0.2894737
  },
  {
    "name": "sumrec",
    "by_3gram_simpson": 0.13636363
  },
  {
    "name": "floyd",
    "by_3gram_simpson": 0.17073172
  },
  {
    "name": "factorialrec",
    "by_3gram_simpson": 0.15200001
  },
  {
    "name": "multtable",
    "by_3gram_simpson": 0.1512605
  },
  {
    "name": "mergesort",
    "by_3gram_simpson": 0.32417583
  },
  {
    "name": "decimaltooctal",
    "by_3gram_simpson": 0.19565219
  },
  {
    "name": "iofile",
    "by_3gram_simpson": 0.1574803
  },
  {
    "name": "romannumerals",
    "by_3gram_simpson": 0.31176472
  },
  {
    "name": "factorial",
    "by_3gram_simpson": 0.144
  },
  {
    "name": "anagram",
    "by_3gram_simpson": 0.22666669
  },
  {
    "name": "binaryadd",
    "by_3gram_simpson": 0.23076922
  },
  {
    "name": "quicksort",
    "by_3gram_simpson": 0.29479766
  },
  {
    "name": "palindrome",
    "by_3gram_simpson": 0.16793895
  },
  {
    "name": "fib",
    "by_3gram_simpson": 0.1574803
  },
  {
    "name": "random",
    "by_3gram_simpson": 0.1574803
  },
  {
    "name": "decimaltohex",
    "by_3gram_simpson": 0.17931032
  },
  {
    "name": "perfect",
    "by_3gram_simpson": 0.20895523
  },
  {
    "name": "concatstrings",
    "by_3gram_simpson": 0.1640625
  },
  {
    "name": "comparestrings",
    "by_3gram_simpson": 0.2733333
  },
  {
    "name": "gcdrec",
    "by_3gram_simpson": 0.19696969
  },
  {
    "name": "binarymult",
    "by_3gram_simpson": 0.23033708
  },
  {
    "name": "binarysearchrec",
    "by_3gram_simpson": 0.25153375
  },
  {
    "name": "selectionsort",
    "by_3gram_simpson": 0.25517243
  },
  {
    "name": "linearsearch",
    "by_3gram_simpson": 0.2638889
  },
  {
    "name": "printinitials",
    "by_3gram_simpson": 0.16666669
  },
  {
    "name": "lcm",
    "by_3gram_simpson": 0.21804512
  },
  {
    "name": "armstrong",
    "by_3gram_simpson": 0.13846153
  },
  {
    "name": "insertionsort",
    "by_3gram_simpson": 0.24025977
  },
  {
    "name": "reverse",
    "by_3gram_simpson": 0.17054266
  }
]