[
  {
    "name": "anagram",
    "by_3gram_simpson": 0.32608694,
    "by_longest_common_substring": 0.9434129
  },
  {
    "name": "armstrong",
    "by_3gram_simpson": 0.28099173,
    "by_longest_common_substring": 0.90536046
  },
  {
    "name": "binaryadd",
    "by_3gram_simpson": 0.38853502,
    "by_longest_common_substring": 0.9216167
  },
  {
    "name": "binarymult",
    "by_3gram_simpson": 0.4494382,
    "by_longest_common_substring": 0.9471947
  },
  {
    "name": "binarysearch",
    "by_3gram_simpson": 0.36619717,
    "by_longest_common_substring": 0.9119367
  },
  {
    "name": "binarysearchrec",
    "by_3gram_simpson": 0.39072847,
    "by_longest_common_substring": 0.949487
  },
  {
    "name": "bubblesort",
    "by_3gram_simpson": 0.32824427,
    "by_longest_common_substring": 0.9103013
  },
  {
    "name": "comparestrings",
    "by_3gram_simpson": 0.31060606,
    "by_longest_common_substring": 0.9337945
  },
  {
    "name": "concatstrings",
    "by_3gram_simpson": 0.26829267,
    "by_longest_common_substring": 0.92446446
  },
  {
    "name": "decimaltobinary",
    "by_3gram_simpson": 0.28099173,
    "by_longest_common_substring": 0.91460973
  },
  {
    "name": "decimaltohex",
    "by_3gram_simpson": 0.34586465,
    "by_longest_common_substring": 0.91934466
  },
  {
    "name": "decimaltooctal",
    "by_3gram_simpson": 0.27868855,
    "by_longest_common_substring": 0.91460973
  },
  {
    "name": "factorial",
    "by_3gram_simpson": 0.28695655,
    "by_longest_common_substring": 0.90472645
  },
  {
    "name": "factorialrec",
    "by_3gram_simpson": 0.1962617,
    "by_longest_common_substring": 0.93026423
  },
  {
    "name": "fib",
    "by_3gram_simpson": 0.21052629,
    "by_longest_common_substring": 0.9265634
  },
  {
    "name": "floyd",
    "by_3gram_simpson": 0.24545455,
    "by_longest_common_substring": 0.8947368
  },
  {
    "name": "frequency",
    "by_3gram_simpson": 0.24347824,
    "by_longest_common_substring": 0.89239174
  },
  {
    "name": "gcd",
    "by_3gram_simpson": 0.25862068,
    "by_longest_common_substring": 0.90255046
  },
  {
    "name": "gcdrec",
    "by_3gram_simpson": 0.15454543,
    "by_longest_common_substring": 0.93303686
  },
  {
    "name": "insertionsort",
    "by_3gram_simpson": 0.34782606,
    "by_longest_common_substring": 0.9050797
  },
  {
    "name": "iofile",
    "by_3gram_simpson": 0.17647058,
    "by_longest_common_substring": 0.89175475
  },
  {
    "name": "lcm",
    "by_3gram_simpson": 0.21929824,
    "by_longest_common_substring": 0.90262455
  },
  {
    "name": "linearsearch",
    "by_3gram_simpson": 0.34108526,
    "by_longest_common_substring": 0.90979564
  },
  {
    "name": "mergesort",
    "by_3gram_simpson": 0.39263803,
    "by_longest_common_substring": 0.95762175
  },
  {
    "name": "minmaxarray",
    "by_3gram_simpson": 0.3174603,
    "by_longest_common_substring": 0.9055002
  },
  {
    "name": "multtable",
    "by_3gram_simpson": 0.19999999,
    "by_longest_common_substring": 0.8969404
  },
  {
    "name": "numtowords",
    "by_3gram_simpson": 0.31205672,
    "by_longest_common_substring": 0.9162304
  },
  {
    "name": "palindrome",
    "by_3gram_simpson": 0.27868855,
    "by_longest_common_substring": 0.90660346
  },
  {
    "name": "perfect",
    "by_3gram_simpson": 0.26495725,
    "by_longest_common_substring": 0.89821076
  },
  {
    "name": "prime",
    "by_3gram_simpson": 0.2916667,
    "by_longest_common_substring": 0.90899396
  },
  {
    "name": "printinitials",
    "by_3gram_simpson": 0.26086956,
    "by_longest_common_substring": 0.8935551
  },
  {
    "name": "pyramid",
    "by_3gram_simpson": 0.19999999,
    "by_longest_common_substring": 0.89377594
  },
  {
    "name": "quicksort",
    "by_3gram_simpson": 0.375,
    "by_longest_common_substring": 0.94264925
  },
  {
    "name": "random",
    "by_3gram_simpson": 0.26086956,
    "by_longest_common_substring": 0.90046656
  },
  {
    "name": "reverse",
    "by_3gram_simpson": 0.25862068,
    "by_longest_common_substring": 0.8988142
  },
  {
    "name": "romannumerals",
    "by_3gram_simpson": 0.43315506,
    "by_longest_common_substring": 0.9648738
  },
  {
    "name": "selectionsort",
    "by_3gram_simpson": 0.3358209,
    "by_longest_common_substring": 0.9066375
  },
  {
    "name": "stringtoASCII",
    "by_3gram_simpson": 0.19090909,
    "by_longest_common_substring": 0.8802502
  },
  {
    "name": "sumrec",
    "by_3gram_simpson": 0.22881359,
    "by_longest_common_substring": 0.93360996
  },
  {
    "name": "vowels",
    "by_3gram_simpson": 0.32558137,
    "by_longest_common_substring": 0.89867675
  }
]